virtualenv_multipython/__init__.py
virtualenv_multipython/discover.py
virtualenv_multipython/py.typed
virtualenv_multipython/tag.py
virtualenv_multipython-0.5.1.dist-info/METADATA
virtualenv_multipython-0.5.1.dist-info/WHEEL
virtualenv_multipython-0.5.1.dist-info/entry_points.txt
virtualenv_multipython-0.5.1.dist-info/licenses/LICENSE
virtualenv_multipython-0.5.1.dist-info/RECORD
