Metadata-Version: 2.4
Name: virtualenv-multipython
Version: 0.5.1
Summary: virtualenv discovery plugin for multipython and tox 4
Project-URL: Homepage, https://github.com/makukha/multipython-plugins#virtualenv-multipython
Project-URL: Repository, https://github.com/makukha/multipython-plugins
Project-URL: Issues, https://github.com/makukha/multipython-plugins/issues
Project-URL: Changelog, https://github.com/makukha/multipython-plugins/tree/main/CHANGELOG.md
Author-email: Michael Makukha <m.makukha@gmail.com>
License: MIT
License-File: LICENSE
Keywords: discovery,multipython,plugin,testing,tox,virtualenv,virtualenv-discovery,virtualenv-plugin
Classifier: Development Status :: 4 - Beta
Classifier: Environment :: Plugins
Classifier: Framework :: tox
Classifier: Intended Audience :: Developers
Classifier: License :: OSI Approved :: MIT License
Classifier: Operating System :: OS Independent
Classifier: Programming Language :: Python
Classifier: Programming Language :: Python :: 2
Classifier: Programming Language :: Python :: 2.7
Classifier: Programming Language :: Python :: 3
Classifier: Programming Language :: Python :: 3.5
Classifier: Programming Language :: Python :: 3.6
Classifier: Programming Language :: Python :: 3.7
Classifier: Programming Language :: Python :: 3.8
Classifier: Programming Language :: Python :: 3.9
Classifier: Programming Language :: Python :: 3.10
Classifier: Programming Language :: Python :: 3.11
Classifier: Programming Language :: Python :: 3.12
Classifier: Programming Language :: Python :: 3.13
Classifier: Programming Language :: Python :: 3.14
Classifier: Programming Language :: Python :: Implementation :: CPython
Classifier: Topic :: Software Development
Classifier: Topic :: Software Development :: Libraries
Classifier: Topic :: Software Development :: Quality Assurance
Classifier: Topic :: Software Development :: Testing
Classifier: Topic :: Utilities
Classifier: Typing :: Typed
Requires-Python: !=3.0,!=3.1,!=3.2,!=3.3,!=3.4,>=2.7
Requires-Dist: virtualenv>=20
Provides-Extra: debug
Requires-Dist: loguru>=0.7; (python_version >= '3.5') and extra == 'debug'
